jpipes/__init__.py
jpipes/cli/__init__.py
jpipes/cli/bootstrap.py
jpipes/cli/main.py
jpipes/cli/controllers/__init__.py
jpipes/cli/controllers/base.py
jpipes/cli/controllers/pipeline.py
jpipes/core/__init__.py
jpipes/core/exc.py
jpipes/core/jenkins.py
jpipes-0.9.5.dist-info/DESCRIPTION.rst
jpipes-0.9.5.dist-info/METADATA
jpipes-0.9.5.dist-info/RECORD
jpipes-0.9.5.dist-info/WHEEL
jpipes-0.9.5.dist-info/entry_points.txt
jpipes-0.9.5.dist-info/metadata.json
jpipes-0.9.5.dist-info/namespace_packages.txt
jpipes-0.9.5.dist-info/top_level.txt
