Metadata-Version: 2.0
Name: jpipes
Version: 0.9.5
Summary: Jenkins Pipeline Automation
Home-page: https://github.com/derks/jpipes
Author: BJ Dierkes
Author-email: derks@datafolklabs.com
License: BSD-three-clause
Platform: UNKNOWN
Requires-Dist: cement
Requires-Dist: colorlog
Requires-Dist: pyYaml
Requires-Dist: requests
